[
  {"text": "سبحان الله", "reference": "33 مرة"},
  {"text": "الحمد لله", "reference": "33 مرة"},
  {"text": "الله أكبر", "reference": "33 مرة"},
  {"text": "لا إله إلا الله وحده لا شريك له، له الملك وله الحمد وهو على كل شيء قدير", "reference": "100 مرة"},
  {"text": "سبحان الله وبحمده", "reference": "100 مرة"},
  {"text": "سبحان الله العظيم وبحمده", "reference": "تملآن الميزان"},
  {"text": "أستغفر الله", "reference": "مائة مرة"},
  {"text": "لا حول ولا قوة إلا بالله", "reference": "كنز من كنوز الجنة"},
  {"text": "اللهم صل وسلم على نبينا محمد", "reference": "10 مرات"},
  {"text": "حسبي الله لا إله إلا هو عليه توكلت وهو رب العرش العظيم", "reference": "7 مرات"},
  {"text": "اللهم إني أسألك العفو والعافية في الدنيا والآخرة", "reference": "دعاء"},
  {"text": "بسم الله الذي لا يضر مع اسمه شيء في الأرض ولا في السماء وهو السميع العليم", "reference": "3 مرات"},
  {"text": "رضيت بالله رباً وبالإسلام ديناً وبمحمد صلى الله عليه وسلم نبياً", "reference": "3 مرات"},
  {"text": "اللهم بك أصبحنا وبك أمسينا وبك نحيا وبك نموت وإليك النشور", "reference": "أذكار الصباح"},
  {"text": "اللهم بك أمسينا وبك أصبحنا وبك نحيا وبك نموت وإليك المصير", "reference": "أذكار المساء"},
  {"text": "اللهم ما أصبح بي من نعمة أو بأحد من خلقك فمنك وحدك لا شريك لك فلك الحمد ولك الشكر", "reference": "أذكار الصباح"},
  {"text": "اللهم إني أعوذ بك من الهم والحزن والعجز والكسل", "reference": "دعاء"},
  {"text": "اللهم إني أعوذ بك من شر ما عملت ومن شر ما لم أعمل", "reference": "دعاء"},
  {"text": "اللهم اغفر لي وارحمني واهدني وعافني وارزقني", "reference": "دعاء"},
  {"text": "يا حي يا قيوم برحمتك أستغيث", "reference": "دعاء"},
  {"text": "اللهم إني أسألك الهدى والتقى والعفاف والغنى", "reference": "دعاء"},
  {"text": "اللهم اكفني بحلالك عن حرامك وأغنني بفضلك عمن سواك", "reference": "دعاء"},
  {"text": "اللهم إني أعوذ بك من الجبن والبخل وغلبة الدين وقهر الرجال", "reference": "دعاء"},
  {"text": "اللهم إني ظلمت نفسي ظلماً كثيراً ولا يغفر الذنوب إلا أنت", "reference": "دعاء"},
  {"text": "اللهم اهدني فيمن هديت وعافني فيمن عافيت", "reference": "دعاء"},
  {"text": "اللهم بارك لنا في يومنا هذا", "reference": "دعاء"},
  {"text": "اللهم أنت ربي لا إله إلا أنت خلقتني وأنا عبدك", "reference": "سيد الاستغفار"},
  {"text": "اللهم إني أعوذ بك من زوال نعمتك وتحول عافيتك", "reference": "دعاء"},
  {"text": "اللهم إني أعوذ بك من شر سمعي ومن شر بصري", "reference": "دعاء"},
  {"text": "اللهم آت نفسي تقواها وزكها أنت خير من زكاها", "reference": "دعاء"},
  {"text": "اللهم اجعل القرآن ربيع قلبي ونور صدري", "reference": "دعاء"},
  {"text": "اللهم ارزقنا حلالاً طيباً مباركاً فيه", "reference": "دعاء"},
  {"text": "اللهم ثبتنا على دينك حتى نلقاك", "reference": "دعاء"},
  {"text": "اللهم اغفر للمؤمنين والمؤمنات والمسلمين والمسلمات", "reference": "دعاء"},
  {"text": "اللهم اجعل آخر كلامنا لا إله إلا الله محمد رسول الله", "reference": "دعاء"},
  {"text": "سبحان الله والحمد لله ولا إله إلا الله والله أكبر", "reference": "أفضل الذكر"},
  {"text": "لا إله إلا أنت سبحانك إني كنت من الظالمين", "reference": "دعاء يونس"},
  {"text": "ربنا آتنا في الدنيا حسنة وفي الآخرة حسنة وقنا عذاب النار", "reference": "دعاء"},
  {"text": "اللهم صل على محمد وعلى آل محمد", "reference": "صلوات"},
  {"text": "اللهم إني أسألك من الخير كله عاجله وآجله", "reference": "دعاء"},
  {"text": "اللهم اجعلنا من الذاكرين الشاكرين الصابرين", "reference": "دعاء"},
  {"text": "اللهم اجعلنا من أهل الجنة", "reference": "دعاء"},
  {"text": "اللهم إني أعوذ بك من العجز والكسل", "reference": "دعاء"},
  {"text": "اللهم اغسل قلبي من الذنوب", "reference": "دعاء"},
  {"text": "اللهم إني أعوذ بك من الحزن والهم", "reference": "دعاء"},
  {"text": "اللهم ارزقني شكر نعمتك", "reference": "دعاء"},
  {"text": "اللهم اجعل عملي كله صالحاً", "reference": "دعاء"},
  {"text": "اللهم تقبل منا إنك أنت السميع العليم", "reference": "دعاء"},
  {"text": "اللهم اغفر لي ذنبي كله", "reference": "دعاء"},
  {"text": "اللهم نظف قلبي من كل سوء", "reference": "دعاء"},
  {"text": "اللهم اجعلني من التوابين", "reference": "دعاء"},
  {"text": "اللهم اجعلني من المتقين", "reference": "دعاء"},
  {"text": "اللهم ارزقني حسن الخاتمة", "reference": "دعاء"},
  {"text": "اللهم إني أعوذ بك من فتنة النار", "reference": "دعاء"},
  {"text": "اللهم إني أعوذ بك من فتنة القبر", "reference": "دعاء"},
  {"text": "اللهم إني أعوذ بك من الدجال", "reference": "دعاء"},
  {"text": "اللهم إني أعوذ بك من شر ما يجلبه الليل", "reference": "دعاء"},
  {"text": "اللهم إني أعوذ بك من شر ما يجلبه النهار", "reference": "دعاء"},
  {"text": "اللهم إني أعوذ بك من شر كل دابة أنت آخذ بناصيتها", "reference": "دعاء"},
  {"text": "اللهم إني أعوذ بك من شر نفسي", "reference": "دعاء"},
  {"text": "اللهم إني أعوذ بك من شر الشيطان", "reference": "دعاء"},
  {"text": "اللهم إني أعوذ بك من الكفر والفقر", "reference": "دعاء"},
  {"text": "اللهم إني أعوذ بك من عذاب القبر", "reference": "دعاء"},
  {"text": "اللهم إني أعوذ بك من عذاب جهنم", "reference": "دعاء"},
  {"text": "اللهم إني أعوذ بك من الغفلة", "reference": "دعاء"},
  {"text": "اللهم إني أعوذ بك من النسيان", "reference": "دعاء"},
  {"text": "اللهم إني أعوذ بك من الكسل", "reference": "دعاء"},
  {"text": "اللهم إني أعوذ بك من الجبن", "reference": "دعاء"},
  {"text": "اللهم إني أعوذ بك من البخل", "reference": "دعاء"},
  {"text": "اللهم إني أعوذ بك من الحسد", "reference": "دعاء"},
  {"text": "اللهم إني أعوذ بك من الغضب", "reference": "دعاء"},
  {"text": "اللهم إني أعوذ بك من الرياء", "reference": "دعاء"},
  {"text": "اللهم إني أعوذ بك من العجب", "reference": "دعاء"},
  {"text": "اللهم إني أعوذ بك من الكبر", "reference": "دعاء"},
  {"text": "اللهم إني أعوذ بك من الحقد", "reference": "دعاء"},
  {"text": "اللهم إني أعوذ بك من الظلم", "reference": "دعاء"},
  {"text": "اللهم إني أعوذ بك من الضيق", "reference": "دعاء"},
  {"text": "اللهم إني أعوذ بك من الفقر", "reference": "دعاء"},
  {"text": "اللهم إني أعوذ بك من المرض", "reference": "دعاء"},
  {"text": "اللهم إني أعوذ بك من الهم", "reference": "دعاء"},
  {"text": "اللهم إني أعوذ بك من الغم", "reference": "دعاء"},
  {"text": "اللهم إني أعوذ بك من الدين", "reference": "دعاء"},
  {"text": "اللهم إني أعوذ بك من قسوة القلب", "reference": "دعاء"},
  {"text": "اللهم إني أعوذ بك من غلظة القلب", "reference": "دعاء"},
  {"text": "اللهم إني أعوذ بك من شح النفس", "reference": "دعاء"},
  {"text": "اللهم إني أعوذ بك من شر الفتن", "reference": "دعاء"},
  {"text": "اللهم إني أعوذ بك من شر ما في الأرض", "reference": "دعاء"},
  {"text": "اللهم إني أعوذ بك من شر ما في السماء", "reference": "دعاء"},
  {"text": "اللهم إني أعوذ بك من شر ما أكره", "reference": "دعاء"},
  {"text": "اللهم إني أعوذ بك من شر ما أخاف", "reference": "دعاء"},
  {"text": "اللهم إني أعوذ بك من شر ما أعلم", "reference": "دعاء"},
  {"text": "اللهم إني أعوذ بك من شر ما لا أعلم", "reference": "دعاء"},
  {"text": "اللهم إني أعوذ بك من شر كل ذي شر", "reference": "دعاء"},
  {"text": "اللهم إني أعوذ بك من شر كل حاسد", "reference": "دعاء"},
  {"text": "اللهم إني أعوذ بك من شر كل متكبر", "reference": "دعاء"},
  {"text": "اللهم إني أعوذ بك من شر كل متجبر", "reference": "دعاء"},
  {"text": "اللهم إني أعوذ بك من شر كل مفسد", "reference": "دعاء"},
  {"text": "اللهم إني أعوذ بك من شر كل مضل", "reference": "دعاء"},
  {"text": "اللهم إني أعوذ بك من شر كل مفتري", "reference": "دعاء"},
  {"text": "اللهم إني أعوذ بك من شر كل مغرور", "reference": "دعاء"},
  {"text": "اللهم إني أعوذ بك من شر كل مغتر", "reference": "دعاء"},
  {"text": "اللهم إني أعوذ بك من شر كل مكذب", "reference": "دعاء"},
  {"text": "اللهم إني أعوذ بك من شر كل منافق", "reference": "دعاء"},
  {"text": "اللهم إني أعوذ بك من شر كل فاسق", "reference": "دعاء"},
  {"text": "اللهم إني أعوذ بك من شر كل كافر", "reference": "دعاء"},
  {"text": "اللهم إني أعوذ بك من شر كل مشرك", "reference": "دعاء"},
  {"text": "اللهم إني أعوذ بك من شر كل ظالم", "reference": "دعاء"},
  {"text": "اللهم إني أعوذ بك من شر كل جبار", "reference": "دعاء"},
  {"text": "اللهم إني أعوذ بك من شر كل عات", "reference": "دعاء"},
  {"text": "اللهم إني أعوذ بك من شر كل مارد", "reference": "دعاء"},
  {"text": "اللهم إني أعوذ بك من شر كل شيطان", "reference": "دعاء"},
  {"text": "اللهم إني أعوذ بك من شر كل جن", "reference": "دعاء"},
  {"text": "اللهم إني أعوذ بك من شر كل إنس", "reference": "دعاء"},
  {"text": "اللهم إني أعوذ بك من شر كل حيوان", "reference": "دعاء"},
  {"text": "اللهم إني أعوذ بك من شر كل جماد", "reference": "دعاء"},
  {"text": "اللهم إني أعوذ بك من شر كل نبات", "reference": "دعاء"},
  {"text": "اللهم إني أعوذ بك من شر كل شيء", "reference": "دعاء"},
  {"text": "اللهم إني أعوذ بك من شر كل أحد", "reference": "دعاء"},
  {"text": "اللهم إني أعوذ بك من شر كل شيء سواك", "reference": "دعاء"}
]
